README.rst
rpsowmi.py
setup.py
rpsowmi.egg-info/PKG-INFO
rpsowmi.egg-info/SOURCES.txt
rpsowmi.egg-info/dependency_links.txt
rpsowmi.egg-info/top_level.txt