Metadata-Version: 1.1
Name: rpsowmi
Version: 2017.4.11
Summary: Remote PowerShell over WMI (RPSoWMI)
Home-page: https://github.com/sakurai-youhei/rpsowmi
Author: Youhei Sakurai
Author-email: sakurai.youhei@gmail.com
License: MIT
Keywords: WMI,PowerShell,Remote
Platform: UNKNOWN
Classifier: License :: OSI Approved :: MIT License
Classifier: Development Status :: 3 - Alpha
Classifier: Programming Language :: Python :: 3.4
Classifier: Programming Language :: Python :: 3.5
Classifier: Programming Language :: Python :: 3.6
Classifier: Operating System :: Microsoft :: Windows
Classifier: Intended Audience :: Developers
